replbuilder/__init__.py
replbuilder/repl_command.py
replbuilder/repl_runner.py
replbuilder-1.2.1.dist-info/METADATA
replbuilder-1.2.1.dist-info/WHEEL
replbuilder-1.2.1.dist-info/top_level.txt
replbuilder-1.2.1.dist-info/RECORD
