Metadata-Version: 2.1
Name: replbuilder
Version: 1.2.1
Summary: Quickly build a custom command REPL environment with this tool
Author-email: Rocky Li <aperocky@gmail.com>
License: MIT
Project-URL: Homepage, https://github.com/Aperocky/replbuilder
Project-URL: Source, https://github.com/Aperocky/replbuilder
Keywords: repl,repl builder
